discogs_track/__init__.py
discogs_track/api.py
discogs_track/artist.py
discogs_track/cli.py
discogs_track/py.typed
discogs_track/record.py
discogs_track/track.py
discogs_track-0.0.2.dist-info/LICENSE.txt
discogs_track-0.0.2.dist-info/METADATA
discogs_track-0.0.2.dist-info/WHEEL
discogs_track-0.0.2.dist-info/entry_points.txt
discogs_track-0.0.2.dist-info/top_level.txt
discogs_track-0.0.2.dist-info/RECORD
