Metadata-Version: 2.1
Name: discogs-track
Version: 0.0.2
Summary: UNKNOWN
Home-page: https://github.com/decitre/discogs_track
Author: Emmanuel Decitre
License: UNKNOWN
Platform: UNKNOWN
Classifier: Programming Language :: Python :: 3 :: Only
Classifier: Programming Language :: Python :: 3.6
Classifier: Programming Language :: Python :: 3.7
Classifier: Programming Language :: Python :: 3.8
Classifier: Programming Language :: Python :: 3.9
Classifier: License :: OSI Approved :: GNU General Public License v3 (GPLv3)
Classifier: Operating System :: OS Independent
Requires-Python: >=3.6
License-File: LICENSE.txt
Requires-Dist: requests
Requires-Dist: responses
Requires-Dist: requests-oauthlib
Requires-Dist: redis
Requires-Dist: ujson
Requires-Dist: tabulate
Requires-Dist: click
Requires-Dist: tqdm
Provides-Extra: dev
Requires-Dist: flake8 ; extra == 'dev'
Requires-Dist: flake8-blind-except ; extra == 'dev'
Requires-Dist: flake8-bugbear ; extra == 'dev'
Requires-Dist: flake8-builtins ; extra == 'dev'
Requires-Dist: flake8-comprehensions ; extra == 'dev'
Requires-Dist: flake8-debugger ; extra == 'dev'
Requires-Dist: flake8-docstrings ; extra == 'dev'
Requires-Dist: flake8-isort ; extra == 'dev'
Requires-Dist: flake8-quotes ; extra == 'dev'
Requires-Dist: flake8-string-format ; extra == 'dev'
Requires-Dist: tox ; extra == 'dev'
Requires-Dist: tox-gh-actions ; extra == 'dev'
Requires-Dist: pytest ; extra == 'dev'
Requires-Dist: pytest-cov ; extra == 'dev'
Requires-Dist: mypy ; extra == 'dev'
Requires-Dist: wheel ; extra == 'dev'
Requires-Dist: check-manifest ; extra == 'dev'
